pyvardump/__init__.py
pyvardump/dump.py
pyvardump/static.py
pyvardump-0.0.5.dist-info/LICENSE
pyvardump-0.0.5.dist-info/METADATA
pyvardump-0.0.5.dist-info/WHEEL
pyvardump-0.0.5.dist-info/top_level.txt
pyvardump-0.0.5.dist-info/RECORD
