Metadata-Version: 2.1
Name: pyvardump
Version: 0.0.5
Summary: pyvardump helps you dump variables in python
Home-page: https://veltzer.github.io/pyvardump
Download-URL: https://github.com/veltzer/pyvardump
Author: Mark Veltzer
Author-email: mark.veltzer@gmail.com
Maintainer: Mark Veltzer
Maintainer-email: mark.veltzer@gmail.com
License: MIT
Keywords: dump,json
Platform: python3
Classifier: Development Status :: 4 - Beta
Classifier: Environment :: Console
Classifier: Operating System :: OS Independent
Classifier: Programming Language :: Python
Classifier: Programming Language :: Python :: 3
Classifier: Programming Language :: Python :: 3 :: Only
Classifier: Programming Language :: Python :: 3.11
Classifier: Topic :: Utilities
Classifier: License :: OSI Approved :: MIT License
License-File: LICENSE
